Metadata-Version: 2.1
Name: testpythonpackage838383883
Version: 0.0.1
Summary: A very basic calculator
Home-page: 
Author: v0rkath
Author-email: x02@fastmail.com
License: MIT
Keywords: calculator
Classifier: Development Status :: 5 - Production/Stable
Classifier: Intended Audience :: Developers
Classifier: Operating System :: Microsoft :: Windows :: Windows 10
Classifier: License :: OSI Approved :: MIT License
Classifier: Programming Language :: Python :: 3
License-File: LICENSE.txt
